linguaf/__init__.py
linguaf/descriptive_statistics.py
linguaf/lexical_diversity.py
linguaf/readability.py
linguaf/syntactical_complexity.py
linguaf/resources/stopwords/be.json
linguaf/resources/stopwords/de.json
linguaf/resources/stopwords/en.json
linguaf/resources/stopwords/es.json
linguaf/resources/stopwords/fr.json
linguaf/resources/stopwords/ru.json
linguaf/resources/stopwords/zh.json
tests/__init__.py
tests/test_descriptive_statistics.py
tests/test_lexical_diversity.py
tests/test_readability.py
tests/test_syntactical_complexity.py
linguaf-0.1.2.dist-info/LICENSE
linguaf-0.1.2.dist-info/METADATA
linguaf-0.1.2.dist-info/WHEEL
linguaf-0.1.2.dist-info/top_level.txt
linguaf-0.1.2.dist-info/RECORD
