Metadata-Version: 2.1
Name: linguaf
Version: 0.1.2
Summary: Python package for calculating famous measures in computational linguistics
Home-page: https://github.com/Perevalov/LinguaF
Author: Aleksandr Perevalov
Author-email: perevalovproduction@gmail.com
License: MIT
Keywords: language features computational linguistics quantitative text analysis
Platform: UNKNOWN
Classifier: Programming Language :: Python
Classifier: Programming Language :: Python :: 3
Classifier: Programming Language :: Python :: 3.6
Classifier: Programming Language :: Python :: 3.7
Classifier: Programming Language :: Python :: 3.8
Classifier: License :: OSI Approved :: MIT License
Classifier: Operating System :: OS Independent
Requires-Python: >=3.6
Requires-Dist: natasha (==1.6.0)
Requires-Dist: nltk (==3.8.1)
Requires-Dist: pymorphy3 (==2.0.2)
Requires-Dist: Pyphen (==0.15.0)
Requires-Dist: pytest (==8.2.0)
Requires-Dist: setuptools (==56.0.0)
Requires-Dist: spacy (==3.7.4)
Requires-Dist: stopwordsiso (==0.6.1)
